{
    "year": 107,
    "term": 1,
    "name": "臺灣近現代藝術專題研究",
    "teachers": [
        "白適銘"
    ],
    "department": "TM60",
    "code": "ATC0249",
    "credit": 3,
    "serial": 3015,
    "group": "",
    "quota": {
        "limit": 50,
        "additional": 20
    },
    "schedule": [
        {
            "day": 3,
            "from": 10,
            "to": 12,
            "campus": "本部",
            "classroom": "美203"
        }
    ],
    "programs": [],
    "comment": "",
    "restrict": "◎課程不開放上修",
    "form_s": "",
    "classes": "8",
    "dept_group": "",
    "hours": 3,
    "description": "在台灣近代史上，攝影的發展，不論是觀念或技術，皆來自於十九世紀以來西方及日本殖民統治的轉介，而成為近代美術史或視覺文化的一部分，至今已超過百年。不論是人類學攝影、紀實攝影(Realistic Photography)、報導攝影(Photo-Reportage)、商業攝影、沙龍攝影、畫意攝影、鄉土攝影、生態攝影，甚或是盛行於今日的數位攝影等，台灣攝影所形構的視覺性歷史，反映從殖民到後殖民時代、文化殖民時代變遷的視覺性重構歷程。一九九○年代之後，急速發展的民主化，台灣社會掙脫極權監控及反思台灣價值的思想轉變，對台灣攝影產生巨大影響，台灣攝影亦因此進入政治、社會、族群、文化、性別等整體性批判之時代。此時，攝影已然超越純然的消費性工具，轉變為台灣戰後時空中歷史再編、反他者凝視、文化主體性及身分認同建構的全新論述載體。",
    "goals": [
        "增進對近代西方、亞洲攝影發展之理解",
        "提升影像理論、技術及歷史研究之能力",
        "強化視覺文化、新媒體研究趨勢之認知",
        "開創跨領域圖像分析論述之綜合能力"
    ],
    "syllabus": "第1週       書目、課程內容介紹\n\n第2-4週     導論(一)(二)(三)：台灣近當代影像藝術研究的基本問題\n\n第5-6週     西方近代攝影及其影像理論發展概述\n\n第9-10週    類型研究─人類學攝影、紀實攝影、報導攝影、商業攝影、沙龍攝影、\n\n             畫意攝影、鄉土攝影、生態攝影、數位攝影\n\n第11週      校外教學(暫定：台北市立美術館)\n\n第12-13週   影像中的「現代」─寫真館與日治時期台灣攝影之萌芽\n\n第14-15週   戰後攝影的歷史敘事與政治批判\n\n第16-17週   身體、凝視、當代性─視覺文化主體的反思\n\n第18週      從攝影、錄像到新媒體─台灣當代影像文化視覺性之形塑",
    "methodologies": [
        {
            "type": "講述法",
            "note": "學期前四週由授課教師進行主題導讀"
        },
        {
            "type": "討論法",
            "note": "本學期每週安排相關文本閱讀及討論"
        },
        {
            "type": "實地考察、參訪",
            "note": "學期中安排1次前往台北當代藝術館進行校外教學"
        },
        {
            "type": "專題研究",
            "note": "修課學生應於期中研擬研究主題，並在課堂發表、討論"
        }
    ],
    "grading": [
        {
            "type": "課堂討論參與",
            "weight": 20,
            "note": "本課程學期成績評量方法，包含：(一)上課出席狀況及平常表現，佔學期總成績之25%。"
        },
        {
            "type": "出席",
            "weight": 5,
            "note": "本課程學期成績評量方法，包含：(一)上課出席狀況及平常表現，佔學期總成績之25%。"
        },
        {
            "type": "報告",
            "weight": 75,
            "note": "(二)平時上課討論資料之閱讀(25%)；(三)期末口頭報告及書面報告(50%)等。期末繳交學期報告(5,000~8,000字)。"
        }
    ],
    "prerequisite": "",
    "general_core": []
}