{
    "year": 110,
    "term": 2,
    "name": "書報討論－科技應用管理（二）",
    "teachers": [
        "蘇友珊"
    ],
    "department": "HM70",
    "code": "IEM0396",
    "credit": 1,
    "serial": 1078,
    "group": "",
    "quota": {
        "limit": 50,
        "additional": 10
    },
    "schedule": [
        {
            "day": 3,
            "from": 7,
            "to": 7,
            "campus": "本部",
            "classroom": "研討二"
        }
    ],
    "programs": [],
    "comment": "",
    "restrict": "◎課程開放上修",
    "form_s": "1",
    "classes": "",
    "dept_group": "",
    "hours": 1,
    "description": "\tThe objective of goals：\n1.\tTo provide the latest professional knowledge in technological application management and enhance the level of research.\n2.\tTo discuss the professional method of research and help students do research.\n\n\tLearning Materials:\nWe’ll offer given reading materials in the course.\n\n\tGrading:\n1.\tPaper Presentation:  50%\nEvery student should present papers in the semester.\n2.\tClass Participation:  50%",
    "goals": [
        "拓展學生對於科技管理領域思維",
        "幫助讓學生對於研究方法之使用"
    ],
    "syllabus": "1.  To provide the new and professional knowledge in the field of technology management and enhance students’ capability of doing research.\n\n2\\.  To discuss the professional research method and help students to understand the skills of doing research.",
    "methodologies": [
        {
            "type": "討論法",
            "note": ""
        },
        {
            "type": "問題解決教學",
            "note": ""
        },
        {
            "type": "合作學習",
            "note": ""
        },
        {
            "type": "專題研究",
            "note": ""
        }
    ],
    "grading": [
        {
            "type": "出席",
            "weight": 10,
            "note": "課堂出席"
        },
        {
            "type": "報告",
            "weight": 90,
            "note": "課堂報告"
        }
    ],
    "prerequisite": "",
    "general_core": []
}