{
    "year": 110,
    "term": 1,
    "name": "英文（一）",
    "teachers": [
        "蘇鈺恩"
    ],
    "department": "CU",
    "code": "00UB7A4",
    "type": "必",
    "grade": null,
    "credit": 2,
    "serial": 281,
    "group": "C",
    "quota": {
        "limit": 35,
        "additional": 0
    },
    "schedule": [
        {
            "day": 1,
            "from": 3,
            "to": 4,
            "campus": "公館",
            "classroom": "Ｓ201"
        }
    ],
    "programs": [],
    "comment": "理學院(數學系、物理系、化學系、生科系、地科系、資工系)、科技學院(光電工程學士學位學程)、營養科學學位學程",
    "restrict": "◎第一階段需人工加選◎第二階段需人工加選◎加退選階段需人工加選",
    "form_s": "",
    "classes": "",
    "dept_group": "",
    "hours": 2,
    "description": "共同科英文（一）課程為一學年課程，每學期兩學分，係為非英語系學生所開設的課程。目標在幫助大一學生活用中學時期所累積的英語知識，提昇英語聽、說、讀、寫整體的溝通能力。為達此目標，本課程要求教師盡量用英語上課，努力營造一個豐富的英語環境，讓學生不但有充分機會以英語參與課堂活動，且樂於使用英語與同學及老師溝通。",
    "goals": [
        "增進學生英語溝通表達能力",
        "透過參與課程活動促進團隊精神",
        "透過多面向英語閱讀促使學生了解多元文化，拓展學生國際化視野",
        "透過課堂討論培養批判精神",
        "提升學生英語學習動機及自主學習興趣"
    ],
    "syllabus": "Instructor: Susan Su 蘇鈺恩\n\nE-mail: [winds10242000@gmail.com](mailto:winds10242000@gmail.com)\n\nDay/Session： Monday 34\n\nClass：公館S201 (共同科 英文一)\n\nTeams Class Code**(****線上授課代碼****)**: **0c8f08j**\n\n **English I (for Non-English Majors)**\n---------------------------------------\n\nFall, 2021\n----------\n\n1.  **教學目標****Objectives:**\n\n  This course aims to help students to develop and improve their English abilities; meanwhile, it also helps to build up students’ confidence and interests in English. Student’s participation, discussion, and group activities in class will be the main focus of this course. Different activities will be offered to guide the students to apply basic English vocabularies, sentences, and grammar to build the familiarity toward English, including using different kinds of visual aids, games, and news...etc. Students will engage in different discussion and practice under the instructor’s guide to improve students’ English speaking, listening, writing, and reading abilities. In addition to understanding the grammar and vocabulary, students are required to have further critical thinking toward the issues, subjects, and contents given in class.\n\n1.  **課本****Textbook:**\n\nMacintyre, Paul & Bohlke, David.  (2019).  **_Reading Explorer: Book 2 (Third Edition)_**_._  National Geographic Learning.\n\n**\\*Please get the book at** **師大書苑** **before 10/4 (the first class).** **同學可直接於師大書院購書，或去海學出版社(位於台北)購買。其餘因個人原因在外縣市或國外的同學請填寫以下表單自行購書(自付運費，有****宅配或全家店到店****)**\n\n**[https://docs.google.com/forms/d/1thtWoZck7uCz35xidqvfFCnAiUH7sa4nD9ucW2sVNog/edit?usp=sharing](https://docs.google.com/forms/d/1thtWoZck7uCz35xidqvfFCnAiUH7sa4nD9ucW2sVNog/edit?usp=sharing)**\n\n**\\*****因應疫情考量，前三周為線上授課，將使用****Microsoft Teams****的系統，請同學下載****Teams****，並加入課程，代碼為****: 0c8f08j** **。如無法用代碼加入的同學，請直接搜尋課程或用以下網址加入課程****: [https://teams.microsoft.com/l/team/19%3aCrCjMte9K-HPTQtf1vynHak5uAoBk6sZPF8Prm1uMyU1%40thread.tacv2/conversations?groupId=3dacf11d-c477-4b6e-a87a-4a73b2221909&tenantId=fde3e8ff-5b61-45a7-981a-1a31b1b9b01b](https://teams.microsoft.com/l/team/19%3aCrCjMte9K-HPTQtf1vynHak5uAoBk6sZPF8Prm1uMyU1%40thread.tacv2/conversations?groupId=3dacf11d-c477-4b6e-a87a-4a73b2221909&tenantId=fde3e8ff-5b61-45a7-981a-1a31b1b9b01b)**\n\n**如無法加入課程請盡快來信詢問老師****!** **往後課程是否為線上或實體教室將於前三周公告說明****!**\n\n1.  **Delivery of instruction (****授課方式****)**\n    1.  Lecture\n    2.  Group discussion & cooperation (Quality Talk)\n    3.  Student presentation\n\n(\\*本課程因疫情影響，會採取滾動式教學調整)\n\n1.  **Weekly Schedule(16+2 weeks): (****課程進度將依實際狀況做適當調整或變更。一切變動皆會在課堂和學生事前告知。****)**\n\nWeek\n\nDate\n\nUnit\n\nAssignment and Content\n\n1\n\n9/27\n\nCourse Introduction 課程介紹\n\nKnowing your classmates, warmup activities\n\n2\n\n10/4\n\n1.  “How to read English articles?”: Reading tips and instruction\n2.  Unit 3A\n\n3\n\n10/11\n\n**國慶日補假****No class**\n\n4\n\n10/18\n\n1.  Unit 3A extra reading; Unit 1A\n2.  Lexile Pre-test (10:20)\n\n第一節課Lexile考試 (Lexile考試方式將再通知同學)，第二節課正常上課\n\n5\n\n10/25\n\nUnit 1A ; Unit 1A extra reading\n\n\\*Think about how to present yourself for the self-introduction\n\n6\n\n11/1\n\n“How to structure and present yourself?”: preparing for self-introduction\n\nOutline your self-introduction\n\n\\*Assignment: self-introduction draft\n\n7\n\n11/8\n\nUnit 2B; oral practice of self-introduction\n\n\\*Hand in the first draft of self-introduction\n\n8\n\n11/15\n\n**期中考周(正常上課)**  \nReview and Practice: self-introduction\n\n\\*Final practice: onstage practice\n\n9\n\n11/22\n\n**Self-introduction (1~2mins)**\n\n**\\*****當天務必準時出席****Please be on time!**\n\n**\\*****當天除上台自我介紹也須同時繳交完整紙本全文** **(due day)**\n\n10\n\n11/29\n\nTed talk reading and games\n\n常見英文錯誤\n\n11\n\n12/6\n\nUnit 4A\n\n12\n\n12/13\n\nNews reading and review\n\n**\\*Decide the final grouping and reporting time**\n\n13\n\n12/20\n\nPreparing for final report, final practice, and wrap up\n\nPrepare for final report\n\n14\n\n12/27\n\n**Final presentation: group presentation**\n\n**期末團體報告開始**\n\n**\\*****當天所有同學務必準時出席****Please be on time!**\n\n15\n\n1/3\n\n**Final presentation: group presentation**\n\n16\n\n1/10\n\n**期末考周**\n\n**Final presentation: group presentation**\n\n17\n\n1/17\n\n**No class**\n\n18\n\n1/24\n\n**No class**\n\n1.  **上課要求與規則****Requirements and Rules:**\n\n1.  If you want to succeed in this class, you need to be willing to devote time participating all the class activities, including class discussion, practice, assignment, and presentation. **Your learning attitude is essential in this class**. You need to focus both on your attendance and class activities. Without joining any class activities, you won’t get a higher score for this class. **(****請注意學習態度，沒有參與課堂活動、討論或練習，也不會獲得高分****)**\n2.  **Attendance is required**. **Missing 4 classes, without telling your teacher in advance (at least “a week” before your absence) with a proper reason, you will be failed for this class. If you’re late, it costs you 1 point every time. Please note that if you’re late for more than 15 minutes, you’ll be absent for that class. For 1 absence, it costs you 2 points every time.** **(****缺席四次，在沒有以「正當理由及原因」事先告知老師下，將無法通過此課程。每次遲到扣一分。缺席一次扣****2****分****(****在線上如未回應會算缺席，請同學注意****)****。****\\*****非必要的私人活動請勿排在正課時間****!** **有任何狀況請記得事先****e-mail****或親自告知老師，請假請以「正當理由及原因」告知老師並補上證明。****)**\n3.  \\*Proper reasons contain:\n\n*   Illness or medical emergency (with proof)\n*   Family emergencies\n*   Pre-arranged school activities (with proof)\n\n1.  **Textbook is a must**. **Violation of this rule will cost you 1 point (out of your final score) each time**. (You can bring no textbook ONLY when teacher informs you!) **(****沒帶課本，每次扣總成績一分，只有在老師提前告知下可不帶課本****)**\n2.  Lexile Pre-test (藍思閱讀測驗): everyone needs to take Lexile pre-test and read the Scholastic Literacy Pro(藍思線上閱讀系統) for 5 hours. (all in 10%) (**請參考共外組的說明登入****: [https://www.aa.ntnu.edu.tw/8intro/super\\_pages.php?ID=6intro73&Sn=290](https://www.aa.ntnu.edu.tw/8intro/super_pages.php?ID=6intro73&Sn=290)**\n\n**，並在本學期累積線上閱讀共五小時，期末校方將統計同學的閱讀總時數，依照系上規定，此閱讀和參加****Lexile****共佔總成績的****10%****，登入帳號和密碼會在之後依校方給的資訊給同學** )\n\n\\*大一新生藍思測驗 Lexile Test\n\nTime: 11/5, 9:10 \\*當天第一節課正常上課(8:15)\n\nPlace: 樸101 \\*是否採取線上或實體考試將再通知同學\n\n1.  Moodle: [https://moodle3.ntnu.edu.tw/](https://moodle3.ntnu.edu.tw/)\n\n\\*google 請搜尋 **師大****moodle 3.7**: Please know how to use moodle and check itfrequently! (**上課的資料、公告或作業上傳將同步放至****moodle****及****Microsoft Teams****及****e-mail** **。請同學務必學習如何操作，並隨時注意老師的公告**。)\n\n1.  **Self-introduction****自我介紹**: We don’t have midterm exam; instead, **you need to write your self-introduction and make a brief presentation in 1~2mins. When you present, you cannot read any notes**.\n2.  **Final presentation** **期末團體報告**: **Followed by teacher’s instruction, each group needs to report and introduce the assigned article by teacher**. **You’ll be scored on voc list, ppt, oral performance, man ideas, important/interesting messages, and individual explanation. (guide the whole class to read/understand the article)** Further information will be given before your presentation.\n3.  **Please check Moodle and e-mail frequently!** It’s your responsibility to make sure you register with the correct email address on Moodle. **Not receiving a notice or forgetting to check is NOT an excuse for any class activities. (****請隨時查****看****Moodle****及老師寄的****e-mail****!** **各種作業、活動因沒有收到通知、不知道或忘了查看而沒做並不是理由。****)**\n4.  **Our syllabus will be adjusted based on the real class schedule. Please make sure you read any notice from teacher’s mail or Moodle. (****實際上課進度將因上課狀況做調整****)**\n5.  This course aims to offer a positive and comfortable learning environment for all the students to learn in a positive, relaxed, happy mood, so **please RESPECT your classmates, your teacher, and this class. Any serious violation of this class might cause great outcome on your final score. If you have any problems/questions, you are always welcome to talk to your teacher.**\n\n1.  **計分****Grading:**\n\nAttendance出席\n\n**20%**\n\nMissing **4** classes, without telling your teacher in advance with a proper reason, you will be failed for this class. Being late for more than 15 minutes is also considered as “absent”. For 1 absence, it costs you 2 points every time.\n\nSelf-introduction\n\n(自我介紹發表及紙本自我介紹)\n\n**25%**\n\n \n\nFinal Presentation 期末報告\n\n**20%**\n\n \n\nLexile Pre-test\n\n**10%**\n\nClass participation and assignment  \n課堂參與、討論及平時作業(課程活動)\n\n**25%**\n\n \n\n1.  **額外加分及補救活動****Extra bonus and Makeup activities:**\n\n**A. Extra bonus**: Joining Oral Reading Competition (英文朗讀比賽) will gain **5 points** for your final score.\n\n**B. Extra bonus and make up activities:** _If you have a poor performance in class, including your learning attitude, attendance, presentation, class participation, you need do 1 makeup activity.(You teacher will inform you in advance) For those who wants extra points for the final score, you can also do 1 of these activities._\n\n**Choose 1 out of the 3 makeup activities:**\n\n1.  **Lexile****讀本閱讀心得報告**: Choose a Lexile book of your Lexile level (based on your Lexile score). Read it, summarize the book, and write your feedback of the reading. You need to write in 500 words. You need to turn in your paper on the last day of this course.\n2.  **參與英文活動或比賽並寫心得報告:**Attend a competition or event held in English and write your feedback on the experience in 500~600 words. You need to introduce the English activity (what is the activity about, what did you do there, what did you learn/gain…etc.) and write your thoughts/feedback about attending this activity. You need to turn in your paper on the last day of this course.\n3.  **去英語自學教室學習英文****(****累積****10****小時****)**: Visit 英語自學教室 (本部樸 101) to use any on-line learning at least for 10 hours, including grammar, listening, and reading. (excluding movies) You don’t have to stay directly for 10 hours a day, it can be accumulated for several times. Please log into the system to record your visits and give me your records by the end of the class. \n\n1.  **Other References** **其他參考資料及英文學習方式**\n    1.  共同教育外文組網站:\n        1.  同學可上共教外文組網站查閱任何相關活動或英文學習的資料\n        2.  [https://www.aa.ntnu.edu.tw/8intro/super\\_pages.php?ID=6intro73](https://www.aa.ntnu.edu.tw/8intro/super_pages.php?ID=6intro73)\n    2.  英語自學教室(Self-Access English Learning Center):樸 101 (PU101)\n        1.  預定開放時間: 2021 年 09 月 22 日至 2022 年 1 月 25 日, 週一至週五 09:00-12:00，13:30-17:00\n    3.  英語工作坊 Workshop: 樸 102(PU 102)\n\n      開放時間詳見外文組網站公告",
    "methodologies": [
        {
            "type": "講述法",
            "note": "focus on students interaction with the classmates' discussion under teacher's instruction."
        },
        {
            "type": "討論法",
            "note": ""
        },
        {
            "type": "問題解決教學",
            "note": ""
        },
        {
            "type": "合作學習",
            "note": ""
        },
        {
            "type": "實驗/實作",
            "note": ""
        },
        {
            "type": "媒體融入教學",
            "note": ""
        }
    ],
    "grading": [
        {
            "type": "期末考",
            "weight": 20,
            "note": "final group presentation"
        },
        {
            "type": "課堂討論參與",
            "weight": 25,
            "note": "class participation and assignment 包含課堂參與、討論及平時作業(課程活動)"
        },
        {
            "type": "出席",
            "weight": 20,
            "note": "Missing 4 classes, without telling your teacher in advance with a proper reason, you will be failed for this class. Being late for more than 20 minutes is also considered as “absent”. For 1 absence, it costs you 2 points every time."
        },
        {
            "type": "報告",
            "weight": 25,
            "note": "self-introduction (onstage presentation and draft)"
        },
        {
            "type": "其他",
            "weight": 10,
            "note": "Lexile Pre-test"
        }
    ],
    "prerequisite": "",
    "general_core": []
}