[
    {
        "year": 107,
        "term": 1,
        "name": "資料結構",
        "teachers": [
            "李良一"
        ],
        "department": "EU11",
        "code": "LSU0003",
        "credit": 3,
        "serial": 889,
        "group": "",
        "quota": {
            "limit": 50,
            "additional": 20
        },
        "schedule": [
            {
                "day": 3,
                "from": 6,
                "to": 8,
                "campus": "本部",
                "classroom": "教404"
            }
        ],
        "programs": [],
        "comment": "",
        "restrict": "",
        "form_s": "",
        "classes": "",
        "dept_group": ""
    },
    {
        "year": 107,
        "term": 1,
        "name": "線上課程設計",
        "teachers": [
            "張欣怡"
        ],
        "department": "EU11",
        "code": "LSU0020",
        "credit": 3,
        "serial": 890,
        "group": "",
        "quota": {
            "limit": 50,
            "additional": 20
        },
        "schedule": [
            {
                "day": 1,
                "from": 2,
                "to": 4,
                "campus": "本部",
                "classroom": "教403"
            }
        ],
        "programs": [],
        "comment": "",
        "restrict": "",
        "form_s": "",
        "classes": "",
        "dept_group": ""
    },
    {
        "year": 107,
        "term": 1,
        "name": "學習心理",
        "teachers": [
            "邱國力"
        ],
        "department": "EU11",
        "code": "LSU0040",
        "credit": 3,
        "serial": 891,
        "group": "",
        "quota": {
            "limit": 50,
            "additional": 20
        },
        "schedule": [
            {
                "day": 2,
                "from": 6,
                "to": 8,
                "campus": "本部",
                "classroom": "樸402"
            }
        ],
        "programs": [],
        "comment": "",
        "restrict": "",
        "form_s": "",
        "classes": "",
        "dept_group": ""
    },
    {
        "year": 107,
        "term": 1,
        "name": "資訊行為",
        "teachers": [
            "林宗進"
        ],
        "department": "EU11",
        "code": "LSU0047",
        "credit": 3,
        "serial": 892,
        "group": "",
        "quota": {
            "limit": 50,
            "additional": 20
        },
        "schedule": [
            {
                "day": 2,
                "from": 2,
                "to": 4,
                "campus": "本部",
                "classroom": "國際會議中心3A會議室"
            }
        ],
        "programs": [],
        "comment": "",
        "restrict": "",
        "form_s": "",
        "classes": "",
        "dept_group": ""
    },
    {
        "year": 107,
        "term": 1,
        "name": "腦與學習",
        "teachers": [
            "梁至中"
        ],
        "department": "EU11",
        "code": "LSU0053",
        "credit": 3,
        "serial": 893,
        "group": "",
        "quota": {
            "limit": 50,
            "additional": 20
        },
        "schedule": [
            {
                "day": 1,
                "from": 6,
                "to": 8,
                "campus": "本部",
                "classroom": "正201"
            }
        ],
        "programs": [],
        "comment": "",
        "restrict": "",
        "form_s": "",
        "classes": "",
        "dept_group": ""
    },
    {
        "year": 107,
        "term": 1,
        "name": "線性代數",
        "teachers": [
            "李良一"
        ],
        "department": "EU11",
        "code": "LSU0058",
        "credit": 3,
        "serial": 894,
        "group": "",
        "quota": {
            "limit": 50,
            "additional": 20
        },
        "schedule": [
            {
                "day": 4,
                "from": 6,
                "to": 8,
                "campus": "本部",
                "classroom": "樸306"
            }
        ],
        "programs": [],
        "comment": "",
        "restrict": "",
        "form_s": "",
        "classes": "",
        "dept_group": ""
    },
    {
        "year": 107,
        "term": 1,
        "name": "體育",
        "teachers": [
            "掌慶維"
        ],
        "department": "EU11",
        "code": "00UP001",
        "credit": 1,
        "serial": 895,
        "group": "",
        "quota": {
            "limit": 50,
            "additional": 20
        },
        "schedule": [
            {
                "day": 4,
                "from": 1,
                "to": 2,
                "campus": "本部",
                "classroom": "操場一"
            }
        ],
        "programs": [],
        "comment": "",
        "restrict": "",
        "form_s": "1",
        "classes": "",
        "dept_group": ""
    },
    {
        "year": 107,
        "term": 1,
        "name": "程式設計（一）",
        "teachers": [
            "蔡孟蓉"
        ],
        "department": "EU11",
        "code": "LSU0001",
        "credit": 3,
        "serial": 896,
        "group": "",
        "quota": {
            "limit": 50,
            "additional": 20
        },
        "schedule": [
            {
                "day": 4,
                "from": 6,
                "to": 8,
                "campus": "本部",
                "classroom": "教402"
            }
        ],
        "programs": [],
        "comment": "",
        "restrict": "",
        "form_s": "1",
        "classes": "",
        "dept_group": ""
    },
    {
        "year": 107,
        "term": 1,
        "name": "學習科學導論",
        "teachers": [
            "李旻憲"
        ],
        "department": "EU11",
        "code": "LSU0005",
        "credit": 3,
        "serial": 897,
        "group": "",
        "quota": {
            "limit": 50,
            "additional": 20
        },
        "schedule": [
            {
                "day": 1,
                "from": 6,
                "to": 8,
                "campus": "本部",
                "classroom": "正203"
            }
        ],
        "programs": [],
        "comment": "",
        "restrict": "",
        "form_s": "1",
        "classes": "",
        "dept_group": ""
    }
]