{
    "year": 108,
    "term": 1,
    "name": "語言與文化",
    "teachers": [
        "楊聰榮"
    ],
    "department": "IU84",
    "code": "CLU1082",
    "credit": 3,
    "serial": 4541,
    "group": "",
    "quota": {
        "limit": 50,
        "additional": 5
    },
    "schedule": [
        {
            "day": 4,
            "from": 8,
            "to": 10,
            "campus": "本部",
            "classroom": "正202"
        }
    ],
    "programs": [],
    "comment": "",
    "restrict": "",
    "form_s": "",
    "classes": "",
    "dept_group": "B",
    "hours": 3,
    "description": "本課程教學目標在利用文化實作的學習與創新，來理解語言與文化的關係，利用傳統經典的語言表達型式，用現代的方式加以創新，以增加文化理解能力，進行推動文化與文化的創生能力。在文化實作的過程中，強調跨語言與跨文化的經驗，學習對其它文化的調適，和文化的衝擊，並學習如何有效將此跨語言與跨文化的經驗運用於華語文教育教學領域中，並討論與語言文化及語言學習的相關重要議題。",
    "goals": [
        "瞭解傳統社會語言文化傳達樣態",
        "瞭解文化與語言之間關係",
        "瞭解跨文化溝通",
        "瞭解華語文教學中跨文化語言學習"
    ],
    "syllabus": "1.緒論/鄉民台語  \n2.語言文化傳承/跳舞時代  \n3.傳統歌曲/紅包場  \n4.Rare Language/sediq  \n5.史豔文  \n6.Artifitial language/Navi Cybertron  \n7.迴文  \n8.Sign Language/The Wizard of Oz  \n9.唸歌  \n10.Words and Language/Processor and Madman  \n11.文夏  \n12.Language and Power/Victoria and Abdul   \n13.勸世歌  \n14.Aborigenal language/Edge of the Knife  \n15.歌仔戲  \n16.Noam Chomsky/Is The Man Who Is Tall Happy?  \n17.相聲  \n18.Multilanguage/Babel Arrival",
    "methodologies": [
        {
            "type": "講述法",
            "note": ""
        },
        {
            "type": "討論法",
            "note": ""
        },
        {
            "type": "問題解決教學",
            "note": ""
        },
        {
            "type": "合作學習",
            "note": ""
        },
        {
            "type": "實地考察、參訪",
            "note": ""
        },
        {
            "type": "媒體融入教學",
            "note": ""
        },
        {
            "type": "專題研究",
            "note": ""
        }
    ],
    "grading": [
        {
            "type": "作業",
            "weight": 30,
            "note": ""
        },
        {
            "type": "課堂討論參與",
            "weight": 30,
            "note": ""
        },
        {
            "type": "出席",
            "weight": 20,
            "note": ""
        },
        {
            "type": "報告",
            "weight": 20,
            "note": ""
        }
    ],
    "prerequisite": "",
    "general_core": []
}